setup.py
czutils/__init__.py
czutils/config.py
czutils/cos_image_uploader.py
czutils/decorators.py
czutils/exceptions.py
czutils/image_loader.py
czutils/network.py
czutils/process_pool.py
czutils/random_number.py
czutils/singleton_metaclass.py
czutils.egg-info/PKG-INFO
czutils.egg-info/SOURCES.txt
czutils.egg-info/dependency_links.txt
czutils.egg-info/requires.txt
czutils.egg-info/top_level.txt