Metadata-Version: 1.0
Name: czutils
Version: 1.0.3
Summary: utils for cztec
Home-page: UNKNOWN
Author: xialang
Author-email: xialang@cztec.com
License: MIT Licence
Keywords: pip,czutils,featureextraction
Platform: any
